[
    { "id": "ねこ", "en": "cat", "pt_BR": "gato", "es": "gato" },
    { "id": "いぬ", "en": "dog", "pt_BR": "cachorro", "es": "perro" },
    { "id": "とり", "en": "bird", "pt_BR": "pássaro", "es": "pájaro" },
    { "id": "うさぎ", "en": "rabbit", "pt_BR": "coelho", "es": "conejo" },
    { "id": "うし", "en": "cow", "pt_BR": "vaca", "es": "vaca" },
    { "id": "うま", "en": "horse", "pt_BR": "cavalo", "es": "caballo" },
    { "id": "ひつじ", "en": "sheep", "pt_BR": "ovelha", "es": "oveja" },
    { "id": "やぎ", "en": "goat", "pt_BR": "cabra", "es": "cabra" },
    { "id": "ぶた", "en": "pig", "pt_BR": "porco", "es": "cerdo" },
    { "id": "むし", "en": "insect", "pt_BR": "inseto", "es": "insecto" },
    { "id": "はち", "en": "bee", "pt_BR": "abelha", "es": "abeja" },
    { "id": "くも", "en": "spider", "pt_BR": "aranha", "es": "araña" },
    { "id": "あり", "en": "ant", "pt_BR": "formiga", "es": "hormiga" },
    { "id": "さかな", "en": "fish", "pt_BR": "peixe", "es": "pez" },
    { "id": "かめ", "en": "turtle", "pt_BR": "tartaruga", "es": "tortuga" },
    { "id": "へび", "en": "snake", "pt_BR": "cobra", "es": "serpiente" },
    { "id": "わに", "en": "crocodile", "pt_BR": "crocodilo", "es": "cocodrilo" },
    { "id": "えび", "en": "shrimp", "pt_BR": "camarão", "es": "camarón" },
    { "id": "かえる", "en": "frog", "pt_BR": "rã", "es": "rana" },
    { "id": "ひ", "en": "sun", "pt_BR": "sol", "es": "sol" },
    { "id": "つき", "en": "moon", "pt_BR": "lua", "es": "Luna" },
    { "id": "やま", "en": "mountain", "pt_BR": "montanha", "es": "montaña" },
    { "id": "どうくつ", "en": "cave", "pt_BR": "caverna", "es": "cueva" },
    { "id": "しま", "en": "island", "pt_BR": "ilha", "es": "isla" },
    { "id": "うみ", "en": "sea", "pt_BR": "mar", "es": "mar" },
    { "id": "かわ", "en": "river", "pt_BR": "rio", "es": "rió" },
    { "id": "いけ", "en": "pond", "pt_BR": "lago", "es": "lago" },
    { "id": "たき", "en": "waterfall", "pt_BR": "cachoeira", "es": "cascada" },
    { "id": "き", "en": "tree", "pt_BR": "árvore", "es": "árbol" },
    { "id": "もり", "en": "forest", "pt_BR": "floresta", "es": "bosque" },
    { "id": "はな", "en": "flower", "pt_BR": "flor", "es": "flor" },
    { "id": "はる", "en": "spring", "pt_BR": "primavera", "es": "primavera" },
    { "id": "なつ", "en": "summer", "pt_BR": "verão", "es": "el verano" },
    { "id": "あき", "en": "fall", "pt_BR": "outono", "es": "otoño" },
    { "id": "ふゆ", "en": "winter", "pt_BR": "inverno", "es": "invierno" },
    { "id": "ゆき", "en": "snow", "pt_BR": "neve", "es": "nieve" },
    { "id": "あめ", "en": "rain", "pt_BR": "chuva", "es": "lluvia" },
    { "id": "あらし", "en": "storm", "pt_BR": "tempestade", "es": "tormenta" },
    { "id": "にじ", "en": "rainbow", "pt_BR": "arco-íris", "es": "arcoíris" },
    { "id": "べんとう", "en": "box lunch", "pt_BR": "lancheira", "es": "almuerzo portátil" },
    { "id": "さしみ", "en": "raw fish", "pt_BR": "peixe cru", "es": "pescado crudo" },
    { "id": "すし", "en": "sushi", "pt_BR": "sushi", "es": "sushi" },
    { "id": "みそしる", "en": "miso soup", "pt_BR": "sopa de missô", "es": "sopa de miso" },
    { "id": "ラーメン", "en": "ramen", "pt_BR": "ramen", "es": "ramen" },
    { "id": "にく", "en": "meat", "pt_BR": "carne", "es": "carne" },
    { "id": "ソーセージ", "en": "sausage", "pt_BR": "salsicha", "es": "embutido" },
    { "id": "たまご", "en": "egg", "pt_BR": "ovo", "es": "huevo" },
    { "id": "はちみつ", "en": "honey", "pt_BR": "mel", "es": "miel" },
    { "id": "にんじん", "en": "carrot", "pt_BR": "cenoura", "es": "zanahoria" },
    { "id": "にんにく", "en": "garlic", "pt_BR": "alho", "es": "ajo" },
    { "id": "レタス", "en": "lettuce", "pt_BR": "alface", "es": "lechuga" },
    { "id": "ブロッコリー", "en": "broccoli", "pt_BR": "brócolis", "es": "brócoli" },
    { "id": "カリフラワー", "en": "cauliflower", "pt_BR": "couve-flor", "es": "coliflor" },
    { "id": "トマト", "en": "tomato", "pt_BR": "tomate", "es": "tomate" },
    { "id": "じゃがいも", "en": "potato", "pt_BR": "batata", "es": "patata" },
    { "id": "なす", "en": "eggplant", "pt_BR": "beringela", "es": "berenjena" },
    { "id": "きのこ", "en": "mushroom", "pt_BR": "cogumelo", "es": "champiñón" },
    { "id": "かぼちゃ", "en": "pumpkin", "pt_BR": "abóbora", "es": "calabaza" },
    { "id": "ピーナッツ", "en": "peanut", "pt_BR": "amendoim", "es": "maní" },
    { "id": "りんご", "en": "apple", "pt_BR": "maçã", "es": "manzana" },
    { "id": "オレンジ", "en": "orange", "pt_BR": "laranja", "es": "naranja" },
    { "id": "バナナ", "en": "banana", "pt_BR": "banana", "es": "plátano" },
    { "id": "すいか", "en": "watermelon", "pt_BR": "melancia", "es": "sandía" },
    { "id": "いちご", "en": "strawberry", "pt_BR": "morango", "es": "fresa" },
    { "id": "パイナップル", "en": "pineapple", "pt_BR": "abacaxi", "es": "piña" },
    { "id": "ぶどう", "en": "grape", "pt_BR": "uva", "es": "uva" },
    { "id": "チェリー", "en": "cherry", "pt_BR": "cereja", "es": "cereza" },
    { "id": "メロン", "en": "melon", "pt_BR": "melão", "es": "melón" },
    { "id": "ココナッツ", "en": "coconut", "pt_BR": "coco", "es": "coco" },
    { "id": "アボカド", "en": "avocado", "pt_BR": "abacate", "es": "palta" },
    { "id": "みず", "en": "water", "pt_BR": "água", "es": "agua" },
    { "id": "コーヒー", "en": "coffee", "pt_BR": "café", "es": "café" },
    { "id": "おちゃ", "en": "tea", "pt_BR": "chá", "es": "té" },
    { "id": "ぎゅうにゅう", "en": "milk", "pt_BR": "leite", "es": "leche" },
    { "id": "おさけ", "en": "alcoholic drink", "pt_BR": "bebida alcoólica", "es": "bebida alcohólica" },
    { "id": "ワイン", "en": "wine", "pt_BR": "vinho", "es": "vino" },
    { "id": "ビール", "en": "beer", "pt_BR": "cerveja", "es": "cerveza" },
    { "id": "くるま", "en": "car", "pt_BR": "carro", "es": "coche" },
    { "id": "タクシー", "en": "taxi", "pt_BR": "táxi", "es": "taxi" },
    { "id": "バス", "en": "bus", "pt_BR": "ônibus", "es": "autobús" },
    { "id": "トラック", "en": "truck", "pt_BR": "caminhão", "es": "camión" },
    { "id": "バイク", "en": "motorcycle", "pt_BR": "motocicleta", "es": "motocicleta" },
    { "id": "じてんしゃ", "en": "bicycle", "pt_BR": "bicicleta", "es": "bicicleta" },
    { "id": "でんしゃ", "en": "train", "pt_BR": "trem", "es": "tren" },
    { "id": "ちかてつ", "en": "subway", "pt_BR": "metrô", "es": "metro" },
    { "id": "ふね", "en": "ship", "pt_BR": "navio", "es": "barco" },
    { "id": "ボート", "en": "boat", "pt_BR": "barco", "es": "bote" },
    { "id": "ひこうき", "en": "airplane", "pt_BR": "avião", "es": "avion" },
    { "id": "ヘリコプター", "en": "helicopter", "pt_BR": "helicóptero", "es": "helicóptero" },
    { "id": "ロケット", "en": "rocket", "pt_BR": "foguete", "es": "cohete" },
    { "id": "えき", "en": "train station", "pt_BR": "estação de trem", "es": "estación de trenes" },
    { "id": "くうこう", "en": "airport", "pt_BR": "aeroporto", "es": "aeropuerto" },
    { "id": "みなと", "en": "harbour", "pt_BR": "porto", "es": "puerto" },
    { "id": "ぎんこう", "en": "bank", "pt_BR": "banco", "es": "banco" },
    { "id": "びょういん", "en": "hospital", "pt_BR": "hospital", "es": "hospital" },
    { "id": "がっこう", "en": "school", "pt_BR": "escola", "es": "escuela" },
    { "id": "としょかん", "en": "library", "pt_BR": "biblioteca", "es": "biblioteca" },
    { "id": "ホテル", "en": "hotel", "pt_BR": "hotel", "es": "hotel" },
    { "id": "こうじょう", "en": "factory", "pt_BR": "fábrica", "es": "fábrica" },
    { "id": "きょうかい", "en": "church", "pt_BR": "igreja", "es": "iglesia" },
    { "id": "どうぶつえん", "en": "zoo", "pt_BR": "zoológico", "es": "zoo" },
    { "id": "みせ", "en": "shop", "pt_BR": "loja", "es": "tienda" },
    { "id": "やっきょく", "en": "pharmacy", "pt_BR": "farmácia", "es": "farmacia" },
    { "id": "バー", "en": "bar", "pt_BR": "bar", "es": "bar" },
    { "id": "デパート", "en": "department store", "pt_BR": "loja de departamento", "es": "grandes almacenes" },
    { "id": "スーパー", "en": "supermarket", "pt_BR": "supermercado", "es": "supermercado" },
    { "id": "きっさてん", "en": "coffee shop", "pt_BR": "cafeteria", "es": "cafetería" },
    { "id": "レストラン", "en": "restaurant", "pt_BR": "restaurante", "es": "restaurante" },
    { "id": "ノート", "en": "notebook", "pt_BR": "caderno", "es": "diario" },
    { "id": "えんぴつ", "en": "pencil", "pt_BR": "lápis", "es": "lápiz" },
    { "id": "けしゴム", "en": "eraser", "pt_BR": "borracha", "es": "borrador" },
    { "id": "ペン", "en": "pen", "pt_BR": "caneta", "es": "bolígrafo" },
    { "id": "ほん", "en": "book", "pt_BR": "livro", "es": "libro" },
    { "id": "つくえ", "en": "desk", "pt_BR": "escrivaninha", "es": "escritorio" },
    { "id": "かみ", "en": "paper", "pt_BR": "papel", "es": "papel" },
    { "id": "はさみ", "en": "scissors", "pt_BR": "tesoura", "es": "tijeras" },
    { "id": "コンピューター", "en": "computer", "pt_BR": "computador", "es": "computadora" },
    { "id": "スマートフォン", "en": "cellphone", "pt_BR": "celular", "es": "teléfono móvil" },
    { "id": "でんわ", "en": "telephone", "pt_BR": "telefone", "es": "teléfono" },
    { "id": "エーティーエム", "en": "atm", "pt_BR": "caixa eletrônico", "es": "cajero automático" },
    { "id": "いえ", "en": "house", "pt_BR": "casa", "es": "casa" },
    { "id": "しんしつ", "en": "bedroom", "pt_BR": "quarto", "es": "habitación" },
    { "id": "だいどころ", "en": "kitchen", "pt_BR": "cozinha", "es": "cocina" },
    { "id": "トイレ", "en": "toilet", "pt_BR": "banheiro", "es": "baño" },
    { "id": "ドア", "en": "door", "pt_BR": "porta", "es": "puerta" },
    { "id": "かぎ", "en": "key", "pt_BR": "chave", "es": "clave" },
    { "id": "まど", "en": "window", "pt_BR": "janela", "es": "ventana" },
    { "id": "たんす", "en": "wardrobe", "pt_BR": "guarda-roupa", "es": "armario" },
    { "id": "いす", "en": "chair", "pt_BR": "cadeira", "es": "silla" },
    { "id": "ソファー", "en": "sofa", "pt_BR": "sofá", "es": "sofá" },
    { "id": "ベッド", "en": "bed", "pt_BR": "cama", "es": "cama" },
    { "id": "れいぞうこ", "en": "refrigerator", "pt_BR": "geladeira", "es": "refrigerador" },
    { "id": "せんたくき", "en": "washing machine", "pt_BR": "máquina de lavar", "es": "lavadora" },
    { "id": "テレビ", "en": "television", "pt_BR": "televisão", "es": "televisión" },
    { "id": "アイロン", "en": "iron", "pt_BR": "ferro de passar", "es": "plancha electrica" },
    { "id": "エアコン", "en": "air-conditioner", "pt_BR": "ar condicionado", "es": "aire acondicionado" },
    { "id": "せんぷうき", "en": "electric fan", "pt_BR": "ventilador elétrico", "es": "ventilador eléctrico" },
    { "id": "でんしレンジ", "en": "microwave", "pt_BR": "microondas", "es": "microondas" },
    { "id": "ストーブ", "en": "stove", "pt_BR": "fogão", "es": "estufa" },
    { "id": "はし", "en": "chopsticks", "pt_BR": "pauzinhos", "es": "palillos" },
    { "id": "グラス", "en": "glass", "pt_BR": "copo", "es": "vaso" },
    { "id": "スプーン", "en": "spoon", "pt_BR": "colher", "es": "cuchara" },
    { "id": "フォーク", "en": "fork", "pt_BR": "faca", "es": "cuchillo" },
    { "id": "しょくど", "en": "dining room", "pt_BR": "sala de jantar", "es": "comedor" },
    { "id": "タオル", "en": "towel", "pt_BR": "toalha", "es": "toalla" },
    { "id": "シャワー", "en": "shower", "pt_BR": "chuveiro", "es": "ducha" },
    { "id": "せっけん", "en": "soap", "pt_BR": "sabão", "es": "jabón" },
    { "id": "シャンプー", "en": "shampoo", "pt_BR": "xampu", "es": "champú" },
    { "id": "はみがきこ", "en": "toothpaste", "pt_BR": "pasta de dente", "es": "pasta dental" },
    { "id": "ティシャツ", "en": "t-shirt", "pt_BR": "camiseta", "es": "camiseta" },
    { "id": "コート", "en": "coat", "pt_BR": "casaco", "es": "saco" },
    { "id": "レインコート", "en": "raincoat", "pt_BR": "capa de chuva", "es": "impermeable" },
    { "id": "パンツ", "en": "underwear", "pt_BR": "roupa de baixo", "es": "ropa interior" },
    { "id": "ジャケット", "en": "jacket", "pt_BR": "jaqueta", "es": "chaqueta" },
    { "id": "ドレス", "en": "dress", "pt_BR": "vestido", "es": "vestir" },
    { "id": "ショーツ", "en": "shorts", "pt_BR": "calção", "es": "bermudas" },
    { "id": "ジーパン", "en": "jeans", "pt_BR": "jeans", "es": "vaqueros" },
    { "id": "イヤリング", "en": "earring", "pt_BR": "brinco", "es": "arete" },
    { "id": "ネックレス", "en": "necklace", "pt_BR": "colar", "es": "collar" },
    { "id": "ベルト", "en": "belt", "pt_BR": "cinto", "es": "cinturón" },
    { "id": "スリッパ", "en": "slippers", "pt_BR": "chinelos", "es": "zapatillas" },
    { "id": "サンダル", "en": "sandals", "pt_BR": "sandálias", "es": "sandalias" },
    { "id": "ブーツ", "en": "boots", "pt_BR": "botas", "es": "botas" },
    { "id": "アメリカ", "en": "The EUA", "pt_BR": "Estados Unidos", "es": "Estados Unidos" },
    { "id": "アルゼンチン", "en": "Argentina", "pt_BR": "Argentina", "es": "Argentina" },
    { "id": "オーストラリア", "en": "Australia", "pt_BR": "Austrália", "es": "Australia" },
    { "id": "ブラジル", "en": "Brazil", "pt_BR": "Brasil", "es": "Brasil" },
    { "id": "チリ", "en": "Chile", "pt_BR": "Chile", "es": "Chile" },
    { "id": "エジプト", "en": "Egypt", "pt_BR": "Egito", "es": "Egipto" },
    { "id": "フランス", "en": "France", "pt_BR": "França", "es": "Francia" },
    { "id": "ドイツ", "en": "Germany", "pt_BR": "Alemanha", "es": "Alemania" },
    { "id": "イギリス", "en": "United Kingdom", "pt_BR": "Reino Unido", "es": "Reino Unido" },
    { "id": "イタリア", "en": "Italy", "pt_BR": "Itália", "es": "Italia" },
    { "id": "にほん", "en": "Japan", "pt_BR": "Japão", "es": "Japón" },
    { "id": "メキシコ", "en": "Mexico", "pt_BR": "México", "es": "México" },
    { "id": "モロッコ", "en": "Morocco", "pt_BR": "Marrocos", "es": "Marruecos" },
    { "id": "ニュージーランド", "en": "New Zealand", "pt_BR": "Nova Zelândia", "es": "Nueva Zelanda" },
    { "id": "ナイジェリア", "en": "Nigeria", "pt_BR": "Nigéria", "es": "Nigeria" },
    { "id": "フィリピン", "en": "Philippines", "pt_BR": "Filipinas", "es": "Filipinas" },
    { "id": "ポルトガル", "en": "Portugal", "pt_BR": "Portugal", "es": "Portugal" },
    { "id": "ロシア", "en": "Russia", "pt_BR": "Rússia", "es": "Rusia" },
    { "id": "みなみアフリカ", "en": "South Africa", "pt_BR": "África do Sul", "es": "Sudáfrica" },
    { "id": "かんこく", "en": "South Korea", "pt_BR": "Coreia do Sul", "es": "Corea del Sur" },
    { "id": "スペイン", "en": "Spain", "pt_BR": "Espanha", "es": "España" },
    { "id": "タイ", "en": "Thailand", "pt_BR": "Tailândia", "es": "Tailandia" },
    { "id": "トルコ", "en": "Turkey", "pt_BR": "Turquia", "es": "Turquia" },
    { "id": "やきゅう", "en": "baseball", "pt_BR": "beisebol", "es": "béisbol" },
    { "id": "すいえい", "en": "swimming", "pt_BR": "natação", "es": "natación" },
    { "id": "ピンポン", "en": "table tennis", "pt_BR": "tênis de mesa", "es": "tenis de mesa" },
    { "id": "サッカー", "en": "soccer", "pt_BR": "futebol", "es": "fútbol" },
    { "id": "テニス", "en": "tennis", "pt_BR": "tênis", "es": "tenis" },
    { "id": "バスケットボール", "en": "basketball", "pt_BR": "basquetebol", "es": "baloncesto" },
    { "id": "バレーボール", "en": "volleyball", "pt_BR": "vôlei", "es": "vóleibol" },
    { "id": "フットボール", "en": "football", "pt_BR": "futebol", "es": "fútbol" },
    { "id": "ラグビー", "en": "rugby", "pt_BR": "rúgbi", "es": "rugby" },
    { "id": "ボクシング", "en": "boxing", "pt_BR": "boxe", "es": "boxeo" },
    { "id": "しろ", "en": "white", "pt_BR": "branco", "es": "blanco" },
    { "id": "くろ", "en": "black", "pt_BR": "preto", "es": "negro" },
    { "id": "あか", "en": "red", "pt_BR": "vermelho", "es": "rojo" },
    { "id": "あお", "en": "blue", "pt_BR": "azul", "es": "azul" },
    { "id": "みどり", "en": "green", "pt_BR": "verde", "es": "verde" },
    { "id": "きいろ", "en": "yellow", "pt_BR": "amarelo", "es": "amarillo" },
    { "id": "ちゃいろ", "en": "brown", "pt_BR": "marrom", "es": "marrón" },
    { "id": "きんいろ", "en": "gold", "pt_BR": "ouro", "es": "oro" },
    { "id": "ぎんいろ", "en": "silver", "pt_BR": "prata", "es": "plata" },
    { "id": "ももいろ", "en": "pink", "pt_BR": "rosa", "es": "rosado" },
    { "id": "だいだいいろ", "en": "orange", "pt_BR": "laranja", "es": "naranja" },
    { "id": "アイスクリーム", "en": "ice cream", "pt_BR": "sorvete", "es": "helado" },
    { "id": "バター", "en": "butter", "pt_BR": "manteiga", "es": "mantequilla" },
    { "id": "ボタン", "en": "button", "pt_BR": "botão", "es": "botón" },
    { "id": "チケット", "en": "ticket", "pt_BR": "bilhete", "es": "billete" },
    { "id": "パン", "en": "bread", "pt_BR": "pão", "es": "pan" },
    { "id": "ピザ", "en": "pizza", "pt_BR": "pizza", "es": "pizza" },
    { "id": "ポテチ", "en": "potato chips", "pt_BR": "batata frita", "es": "patatas fritas" },
    { "id": "サンドイッチ", "en": "sandwich", "pt_BR": "sanduíche", "es": "sandwich" },
    { "id": "サラダ", "en": "salad", "pt_BR": "salada", "es": "ensalada" }
]